bsvn/__init__.py
bsvn/access_file.py
bsvn/access_file_test.py
bsvn/svn.py
bsvn-0.3.1.dist-info/METADATA
bsvn-0.3.1.dist-info/RECORD
bsvn-0.3.1.dist-info/WHEEL
bsvn-0.3.1.dist-info/top_level.txt
