Metadata-Version: 2.1
Name: bsvn
Version: 0.3.1
Summary: Subversion interface library
Home-page: https://github.com/BlackEarth/bsvn
Author: Sean Harrison
Author-email: sah@blackearthgroup.com
License: LGPL 3.0
Platform: UNKNOWN
Classifier: Development Status :: 4 - Beta
Classifier: Intended Audience :: Developers
Classifier: License :: OSI Approved :: GNU Library or Lesser General Public License (LGPL)
Classifier: Programming Language :: Python :: 3
Provides-Extra: dev
Provides-Extra: test
Requires-Dist: bl
Requires-Dist: bxml
Provides-Extra: dev
Provides-Extra: test
